ElasticMock-1.3.4.dist-info/DESCRIPTION.rst
ElasticMock-1.3.4.dist-info/METADATA
ElasticMock-1.3.4.dist-info/RECORD
ElasticMock-1.3.4.dist-info/WHEEL
ElasticMock-1.3.4.dist-info/metadata.json
ElasticMock-1.3.4.dist-info/top_level.txt
elasticmock/__init__.py
elasticmock/fake_elasticsearch.py
elasticmock/utilities/__init__.py
tests/__init__.py
tests/test_elasticmock.py
