Metadata-Version: 2.0
Name: ElasticMock
Version: 1.3.4
Summary: Python Elasticsearch Mock for test purposes
Home-page: https://github.com/vrcmarcos/elasticmock
Author: Marcos Cardoso
Author-email: vrcmarcos@gmail.com
License: UNKNOWN
Platform: UNKNOWN
Classifier: Environment :: Web Environment
Classifier: Intended Audience :: Developers
Classifier: Operating System :: OS Independent
Classifier: Programming Language :: Python :: 3
Classifier: License :: OSI Approved :: MIT License
Classifier: Topic :: Software Development :: Libraries :: Python Modules
Requires-Dist: elasticsearch
Requires-Dist: mock
